Automunge/Automunger.py
Automunge/__init__.py
Automunge-3.18.dist-info/LICENSE
Automunge-3.18.dist-info/METADATA
Automunge-3.18.dist-info/WHEEL
Automunge-3.18.dist-info/top_level.txt
Automunge-3.18.dist-info/RECORD
