Metadata-Version: 2.1
Name: Automunge
Version: 3.18
Summary: A tool for automated data wrangling
Home-page: https://github.com/Automunge/AutoMunge
Author: Nicholas Teague
Author-email: pitg888@gmail.com
License: UNKNOWN
Platform: UNKNOWN
Classifier: Programming Language :: Python :: 3
Classifier: License :: OSI Approved :: GNU General Public License v3 (GPLv3)
Classifier: Operating System :: OS Independent
Requires-Dist: numpy
Requires-Dist: pandas
Requires-Dist: scikit-learn
Requires-Dist: scipy
